.coveragerc
CONTRIBUTING.md
LICENSE
MANIFEST.in
README.md
TigerLilyReport.pdf
example_notebook.ipynb
pyproject.toml
setup.cfg
setup.py
script/personalized_pagerank.gqsl
tests/test_tigerlily.py
tigerlily/__init__.py
tigerlily/dataset.py
tigerlily/embedding.py
tigerlily/operator.py
tigerlily/pagerank.py
tigerlily/version.py
tigerlily.egg-info/PKG-INFO
tigerlily.egg-info/SOURCES.txt
tigerlily.egg-info/dependency_links.txt
tigerlily.egg-info/requires.txt
tigerlily.egg-info/top_level.txt
tigerlily/__pycache__/__init__.cpython-38.pyc
tigerlily/__pycache__/dataset.cpython-38.pyc
tigerlily/__pycache__/embedding.cpython-38.pyc
tigerlily/__pycache__/operator.cpython-38.pyc
tigerlily/__pycache__/pagerank.cpython-38.pyc
tigerlily/__pycache__/version.cpython-38.pyc