Metadata-Version: 2.1
Name: tigerlily
Version: 0.1.0
Summary: TigerLily: Finding drug interactions in-silico with the Graph.
Home-page: https://github.com/benedekrozemberczki/tigerlily
Author: Benedek Rozemberczki
Author-email: benedek.rozemberczki@gmail.com
License: Apache License, Version 2.0
Download-URL: https://github.com/benedekrozemberczki/tigerlily/archive/v0.1.0.tar.gz
Keywords: drug-combination,drug-interaction
Platform: UNKNOWN
Classifier: Development Status :: 3 - Alpha
Classifier: Intended Audience :: Developers
Classifier: Topic :: Software Development :: Build Tools
Classifier: License :: OSI Approved :: Apache Software License
Classifier: Programming Language :: Python :: 3.7
Classifier: Programming Language :: Python :: 3.8
Classifier: Programming Language :: Python :: 3.9
Provides-Extra: tests
Provides-Extra: docs
